{
	"configurations" : 
	[
		{
			"directories" : 
			[
				{
					"build" : ".",
					"childIndexes" : 
					[
						1
					],
					"jsonFile" : "directory-.-Debug-d0094a50bb2071803777.json",
					"minimumCMakeVersion" : 
					{
						"string" : "3.22"
					},
					"projectIndex" : 0,
					"source" : ".",
					"targetIndexes" : 
					[
						0,
						1,
						2,
						3,
						4,
						5,
						6,
						7,
						8,
						9,
						10,
						11,
						12,
						13,
						14,
						15,
						16,
						17,
						18,
						19,
						20,
						21,
						22,
						23,
						24,
						25,
						26,
						27,
						29
					]
				},
				{
					"build" : "ScratchQL",
					"jsonFile" : "directory-ScratchQL-Debug-9ff11d622d2a1e5d8b28.json",
					"minimumCMakeVersion" : 
					{
						"string" : "3.22"
					},
					"parentIndex" : 0,
					"projectIndex" : 0,
					"source" : "ScratchQL",
					"targetIndexes" : 
					[
						28
					]
				}
			],
			"name" : "Debug",
			"projects" : 
			[
				{
					"directoryIndexes" : 
					[
						0,
						1
					],
					"name" : "ScratchQL",
					"targetIndexes" : 
					[
						0,
						1,
						2,
						3,
						4,
						5,
						6,
						7,
						8,
						9,
						10,
						11,
						12,
						13,
						14,
						15,
						16,
						17,
						18,
						19,
						20,
						21,
						22,
						23,
						24,
						25,
						26,
						27,
						28,
						29
					]
				}
			],
			"targets" : 
			[
				{
					"directoryIndex" : 0,
					"id" : "Continuous::@6890427a1f51a3e7e1df",
					"jsonFile" : "target-Continuous-Debug-c1f7f72a1c9463c8a4c8.json",
					"name" : "Continuous",
					"projectIndex" : 0
				},
				{
					"directoryIndex" : 0,
					"id" : "ContinuousBuild::@6890427a1f51a3e7e1df",
					"jsonFile" : "target-ContinuousBuild-Debug-05bca6c36202cf49f8d2.json",
					"name" : "ContinuousBuild",
					"projectIndex" : 0
				},
				{
					"directoryIndex" : 0,
					"id" : "ContinuousConfigure::@6890427a1f51a3e7e1df",
					"jsonFile" : "target-ContinuousConfigure-Debug-e55e39f51c0cb3cb6d2a.json",
					"name" : "ContinuousConfigure",
					"projectIndex" : 0
				},
				{
					"directoryIndex" : 0,
					"id" : "ContinuousCoverage::@6890427a1f51a3e7e1df",
					"jsonFile" : "target-ContinuousCoverage-Debug-334592a3252152fa027d.json",
					"name" : "ContinuousCoverage",
					"projectIndex" : 0
				},
				{
					"directoryIndex" : 0,
					"id" : "ContinuousMemCheck::@6890427a1f51a3e7e1df",
					"jsonFile" : "target-ContinuousMemCheck-Debug-a7c6cf78124d380c9767.json",
					"name" : "ContinuousMemCheck",
					"projectIndex" : 0
				},
				{
					"directoryIndex" : 0,
					"id" : "ContinuousStart::@6890427a1f51a3e7e1df",
					"jsonFile" : "target-ContinuousStart-Debug-b3d9c26483ddc09c3248.json",
					"name" : "ContinuousStart",
					"projectIndex" : 0
				},
				{
					"directoryIndex" : 0,
					"id" : "ContinuousSubmit::@6890427a1f51a3e7e1df",
					"jsonFile" : "target-ContinuousSubmit-Debug-9915106d4582053384a6.json",
					"name" : "ContinuousSubmit",
					"projectIndex" : 0
				},
				{
					"directoryIndex" : 0,
					"id" : "ContinuousTest::@6890427a1f51a3e7e1df",
					"jsonFile" : "target-ContinuousTest-Debug-29c2d2faeb47a36f8abb.json",
					"name" : "ContinuousTest",
					"projectIndex" : 0
				},
				{
					"directoryIndex" : 0,
					"id" : "ContinuousUpdate::@6890427a1f51a3e7e1df",
					"jsonFile" : "target-ContinuousUpdate-Debug-d6b190ee6e0ece0ce41a.json",
					"name" : "ContinuousUpdate",
					"projectIndex" : 0
				},
				{
					"directoryIndex" : 0,
					"id" : "Experimental::@6890427a1f51a3e7e1df",
					"jsonFile" : "target-Experimental-Debug-d5777a5640fedf318a14.json",
					"name" : "Experimental",
					"projectIndex" : 0
				},
				{
					"directoryIndex" : 0,
					"id" : "ExperimentalBuild::@6890427a1f51a3e7e1df",
					"jsonFile" : "target-ExperimentalBuild-Debug-dc6f736f6b83e5a7b103.json",
					"name" : "ExperimentalBuild",
					"projectIndex" : 0
				},
				{
					"directoryIndex" : 0,
					"id" : "ExperimentalConfigure::@6890427a1f51a3e7e1df",
					"jsonFile" : "target-ExperimentalConfigure-Debug-34c283ffb2934c5dd5e6.json",
					"name" : "ExperimentalConfigure",
					"projectIndex" : 0
				},
				{
					"directoryIndex" : 0,
					"id" : "ExperimentalCoverage::@6890427a1f51a3e7e1df",
					"jsonFile" : "target-ExperimentalCoverage-Debug-8347176e031d650064c1.json",
					"name" : "ExperimentalCoverage",
					"projectIndex" : 0
				},
				{
					"directoryIndex" : 0,
					"id" : "ExperimentalMemCheck::@6890427a1f51a3e7e1df",
					"jsonFile" : "target-ExperimentalMemCheck-Debug-a1d9f5a42e4021a9b184.json",
					"name" : "ExperimentalMemCheck",
					"projectIndex" : 0
				},
				{
					"directoryIndex" : 0,
					"id" : "ExperimentalStart::@6890427a1f51a3e7e1df",
					"jsonFile" : "target-ExperimentalStart-Debug-7871c731fb2013986397.json",
					"name" : "ExperimentalStart",
					"projectIndex" : 0
				},
				{
					"directoryIndex" : 0,
					"id" : "ExperimentalSubmit::@6890427a1f51a3e7e1df",
					"jsonFile" : "target-ExperimentalSubmit-Debug-157eff03b88b79f66bde.json",
					"name" : "ExperimentalSubmit",
					"projectIndex" : 0
				},
				{
					"directoryIndex" : 0,
					"id" : "ExperimentalTest::@6890427a1f51a3e7e1df",
					"jsonFile" : "target-ExperimentalTest-Debug-e18bf368a49d9fd9bcf3.json",
					"name" : "ExperimentalTest",
					"projectIndex" : 0
				},
				{
					"directoryIndex" : 0,
					"id" : "ExperimentalUpdate::@6890427a1f51a3e7e1df",
					"jsonFile" : "target-ExperimentalUpdate-Debug-7fff9de4146d9f4d67b4.json",
					"name" : "ExperimentalUpdate",
					"projectIndex" : 0
				},
				{
					"directoryIndex" : 0,
					"id" : "Nightly::@6890427a1f51a3e7e1df",
					"jsonFile" : "target-Nightly-Debug-f4e6c03b58c614252ce5.json",
					"name" : "Nightly",
					"projectIndex" : 0
				},
				{
					"directoryIndex" : 0,
					"id" : "NightlyBuild::@6890427a1f51a3e7e1df",
					"jsonFile" : "target-NightlyBuild-Debug-47f0856252307a5a1f10.json",
					"name" : "NightlyBuild",
					"projectIndex" : 0
				},
				{
					"directoryIndex" : 0,
					"id" : "NightlyConfigure::@6890427a1f51a3e7e1df",
					"jsonFile" : "target-NightlyConfigure-Debug-dccb5b2b6d7da38bdc21.json",
					"name" : "NightlyConfigure",
					"projectIndex" : 0
				},
				{
					"directoryIndex" : 0,
					"id" : "NightlyCoverage::@6890427a1f51a3e7e1df",
					"jsonFile" : "target-NightlyCoverage-Debug-b05c08879753f709b2ac.json",
					"name" : "NightlyCoverage",
					"projectIndex" : 0
				},
				{
					"directoryIndex" : 0,
					"id" : "NightlyMemCheck::@6890427a1f51a3e7e1df",
					"jsonFile" : "target-NightlyMemCheck-Debug-4fe3472a4bf99c97a3b8.json",
					"name" : "NightlyMemCheck",
					"projectIndex" : 0
				},
				{
					"directoryIndex" : 0,
					"id" : "NightlyMemoryCheck::@6890427a1f51a3e7e1df",
					"jsonFile" : "target-NightlyMemoryCheck-Debug-bfa4637d89417efb05b0.json",
					"name" : "NightlyMemoryCheck",
					"projectIndex" : 0
				},
				{
					"directoryIndex" : 0,
					"id" : "NightlyStart::@6890427a1f51a3e7e1df",
					"jsonFile" : "target-NightlyStart-Debug-d5a8ca0eca4f88a71b67.json",
					"name" : "NightlyStart",
					"projectIndex" : 0
				},
				{
					"directoryIndex" : 0,
					"id" : "NightlySubmit::@6890427a1f51a3e7e1df",
					"jsonFile" : "target-NightlySubmit-Debug-261861d31927e10432c0.json",
					"name" : "NightlySubmit",
					"projectIndex" : 0
				},
				{
					"directoryIndex" : 0,
					"id" : "NightlyTest::@6890427a1f51a3e7e1df",
					"jsonFile" : "target-NightlyTest-Debug-3f22e60a7154332f8aca.json",
					"name" : "NightlyTest",
					"projectIndex" : 0
				},
				{
					"directoryIndex" : 0,
					"id" : "NightlyUpdate::@6890427a1f51a3e7e1df",
					"jsonFile" : "target-NightlyUpdate-Debug-c58f87841f53d5859127.json",
					"name" : "NightlyUpdate",
					"projectIndex" : 0
				},
				{
					"directoryIndex" : 1,
					"id" : "ScratchQL_lib::@efc84c30f8a21a457e0b",
					"jsonFile" : "target-ScratchQL_lib-Debug-88f78b63ca17daa6c971.json",
					"name" : "ScratchQL_lib",
					"projectIndex" : 0
				},
				{
					"directoryIndex" : 0,
					"id" : "interface::@6890427a1f51a3e7e1df",
					"jsonFile" : "target-interface-Debug-7898220668d5c33ee192.json",
					"name" : "interface",
					"projectIndex" : 0
				}
			]
		}
	],
	"kind" : "codemodel",
	"paths" : 
	{
		"build" : "C:/Users/enzod/Desktop/ORI/Project/cmake-build-debug",
		"source" : "C:/Users/enzod/Desktop/ORI/Project"
	},
	"version" : 
	{
		"major" : 2,
		"minor" : 7
	}
}
